<?xml version="1.0" encoding="UTF-8"?>
<objects serializationModel="Studio.01.08.00">
    <object class="AudioFile" id="{a9c5ceb5-9875-4af2-97ab-89e002233518}">
        <property name="assetPath">
            <value>3BOT 1.cm_01.wav</value>
        </property>
        <property name="isStreaming">
            <value>true</value>
        </property>
        <property name="frequencyInKHz">
            <value>48</value>
        </property>
        <property name="channelCount">
            <value>2</value>
        </property>
        <property name="length">
            <value>16.844166666666666</value>
        </property>
        <relationship name="masterAssetFolder">
            <destination>{3b91e612-5ac2-4442-83e6-5eeca6dbba07}</destination>
        </relationship>
    </object>
</objects>
