<?xml version="1.0" encoding="UTF-8"?>
<objects serializationModel="Studio.01.08.00">
    <object class="AudioFile" id="{ce180f4e-e0bf-40d5-96e7-a059b4d4cd1f}">
        <property name="assetPath">
            <value>Footsteps Tile_11.wav</value>
        </property>
        <property name="frequencyInKHz">
            <value>48</value>
        </property>
        <property name="channelCount">
            <value>2</value>
        </property>
        <property name="length">
            <value>0.43533333333333335</value>
        </property>
        <relationship name="masterAssetFolder">
            <destination>{3b91e612-5ac2-4442-83e6-5eeca6dbba07}</destination>
        </relationship>
    </object>
</objects>
